tk_oddbox/__init__.py
tk_oddbox/const.py
tk_oddbox/image_label.py
tk_oddbox/image_menu_button.py
tk_oddbox/images.py
tk_oddbox/slice_var.py
tk_oddbox-0.0.4.dist-info/WHEEL
tk_oddbox-0.0.4.dist-info/METADATA
tk_oddbox-0.0.4.dist-info/RECORD
