Metadata-Version: 2.1
Name: tk-oddbox
Version: 0.0.4
Summary: Odd tkinter utilities, including image menu button
License: MIT
Author: Andrew Allaire
Author-email: andrew.allaire@gmail.com
Requires-Python: >=3.5,<4.0
Classifier: License :: OSI Approved :: MIT License
Classifier: Programming Language :: Python :: 3
Classifier: Programming Language :: Python :: 3.5
Classifier: Programming Language :: Python :: 3.6
Classifier: Programming Language :: Python :: 3.7
Classifier: Programming Language :: Python :: 3.8
